dssdata/__init__.py
dssdata/_formatters.py
dssdata/_tools.py
dssdata/decorators/__init__.py
dssdata/pfmodes/__init__.py
dssdata/reductions/__init__.py
dssdata/reductions/regs/__init__.py
dssdata/tools/__init__.py
dssdata/tools/lines/__init__.py
dssdata/tools/losses/__init__.py
dssdata/tools/regs/__init__.py
dssdata/tools/voltages/__init__.py
dssdata-0.2.0.dist-info/LICENSE
dssdata-0.2.0.dist-info/METADATA
dssdata-0.2.0.dist-info/WHEEL
dssdata-0.2.0.dist-info/RECORD
