Metadata-Version: 2.1
Name: dssdata
Version: 0.2.0
Summary: Organizing OpenDSS data
Home-page: https://github.com/felipemarkson/dssdata
License: MIT
Author: Felipe M. S. Monteiro
Author-email: fmarkson@outlook.com
Requires-Python: >=3.9,<4.0
Classifier: Development Status :: 4 - Beta
Classifier: Intended Audience :: Science/Research
Classifier: License :: OSI Approved :: MIT License
Classifier: Programming Language :: Python :: 3
Classifier: Programming Language :: Python :: 3.9
Classifier: Programming Language :: Python :: 3.10
Classifier: Programming Language :: Python :: 3.11
Classifier: Topic :: Software Development :: Libraries :: Python Modules
Requires-Dist: OpenDSSDirect.py (>=0.8.0,<0.9.0)
Requires-Dist: pandas (>=1.0.0,<2.0.0)
Project-URL: Documentation, https://felipemarkson.github.io/dssdata/
Project-URL: Repository, https://github.com/felipemarkson/dssdata
